CHANGELOG.md
bootloader/__init__.py
bootloader/humantrainer/__init__.py
bootloader/humantrainer/constant/uasset.py
bootloader/humantrainer/model/__init__.py
bootloader/humantrainer/model/uasset.py
bootloader/humantrainer/model/uasset_deprecated.py
bootloader/humantrainer/utils/__init__.py
bootloader/humantrainer/utils/uasset_validator.py
bootloader_uassets_validator-0.0.1.dist-info/LICENSE
bootloader_uassets_validator-0.0.1.dist-info/WHEEL
bootloader_uassets_validator-0.0.1.dist-info/METADATA
bootloader_uassets_validator-0.0.1.dist-info/RECORD
