Metadata-Version: 2.1
Name: bootloader-uassets-validator
Version: 0.0.1
Summary: Human Trainer asset file names validator
Home-page: https://github.com/Bootloader-Studio/draft-tool-asset-validator
License: Proprietary
Keywords: tool,utility,humantrainer,naming,convention,validation
Author: Daniel CAUNE
Author-email: daniel.caune@gmail.com
Requires-Python: >=3.9,<4.0
Classifier: Development Status :: 5 - Production/Stable
Classifier: License :: Other/Proprietary License
Classifier: Operating System :: OS Independent
Classifier: Programming Language :: Python
Classifier: Programming Language :: Python :: 3
Classifier: Programming Language :: Python :: 3.9
Classifier: Programming Language :: Python :: 3.10
Classifier: Programming Language :: Python :: 3.11
Classifier: Topic :: Software Development :: Libraries
Requires-Dist: perseus-core-library (>=1.18.21,<2.0.0)
Project-URL: Repository, https://github.com/Bootloader-Studio/draft-tool-asset-validator
